lakectl/__init__.py
lakectl/__main__.py
lakefs/__init__.py
lakefs/__main__.py
lakefs/auth.py
lakefs/branch.py
lakefs/client.py
lakefs/config.py
lakefs/exceptions.py
lakefs/import_manager.py
lakefs/models.py
lakefs/namedtuple.py
lakefs/object.py
lakefs/py.typed
lakefs/reference.py
lakefs/repository.py
lakefs/tag.py
lakefs/download/__init__.py
lakefs/download/__main__.py
lakefs/quickstart/__init__.py
lakefs/quickstart/__main__.py
tests/integration/__init__.py
tests/integration/conftest.py
tests/integration/test_branch.py
tests/integration/test_import.py
tests/integration/test_object.py
tests/integration/test_reference.py
tests/integration/test_repository.py
tests/integration/test_sanity.py
tests/utests/__init__.py
tests/utests/common.py
tests/utests/test_auth.py
tests/utests/test_branch.py
tests/utests/test_client.py
tests/utests/test_exceptions.py
tests/utests/test_import.py
tests/utests/test_namedtuple.py
tests/utests/test_object.py
tests/utests/test_reference.py
tests/utests/test_repository.py
tests/utests/test_tag.py
lakefs-0.14.0.dist-info/METADATA
lakefs-0.14.0.dist-info/WHEEL
lakefs-0.14.0.dist-info/top_level.txt
lakefs-0.14.0.dist-info/RECORD
