Metadata-Version: 2.4
Name: lakefs
Version: 0.14.0
Summary: lakeFS Python SDK Wrapper
Home-page: https://github.com/treeverse/lakeFS/tree/master/clients/python-wrapper
Author: Treeverse
Author-email: services@treeverse.io
License: Apache 2.0
Keywords: OpenAPI,OpenAPI-Generator,lakeFS API,Python Wrapper
Requires-Python: >=3.9
Requires-Dist: lakefs-sdk<2,>=1.50
Requires-Dist: pyyaml~=6.0.1
Provides-Extra: all
Requires-Dist: boto3>=1.26.0; extra == "all"
Provides-Extra: aws-iam
Requires-Dist: boto3>=1.26.0; extra == "aws-iam"
Dynamic: author
Dynamic: author-email
Dynamic: description
Dynamic: description-content-type
Dynamic: home-page
Dynamic: keywords
Dynamic: license
Dynamic: provides-extra
Dynamic: requires-dist
Dynamic: requires-python
Dynamic: summary
